Workbook
Name _F: #REF!
Name _TY1: #REF!
Name _TY1: #REF!
Name CADUCIDAD: [1]PT!$A$1:$D$3551
Name CADUCIDAD: [2]PT!$A$1:$D$3551
Name d: #REF!
Name d: #REF!
Name ESPECIFICACIONES: '[3]INTRODUCCION DE DATOS'!$A$1:$AC$1012
Name ESPECIFICACIONES: '[4]INTRODUCCION DE DATOS'!$A$1:$AC$1012
Name gmroi: '[5]GMROI YR END 08'!#REF!
Name gmroi: '[6]GMROI YR END 08'!#REF!
Name index: #REF!
Name index: #REF!
Name KEM: '[7]INTRODUCCION DE DATOS'!$A$1:$AC$1012
Name KEM: '[8]INTRODUCCION DE DATOS'!$A$1:$AC$1012
Name margmroi: #REF!
Name margmroi: #REF!
Name matt: #REF!
Name matt: #REF!
Name MODIFICACIONES: #REF!
Name MODIFICACIONES: #REF!
Name mp: #REF!
Name mp: #REF!
Name newtrans: #REF!
Name newtrans: #REF!
Name notused: #REF!
Name notused: #REF!
Name pm: #REF!
Name pm: #REF!
Name prices: [9]transfers!$B$2:$C$599
Name prices: [10]transfers!$B$2:$C$599
Name PRODUCTOS: #REF!
Name rex: #REF!
Name rex: #REF!
Name sheet3: #REF!
Name sheet3: #REF!
Name SS: #REF!
Name SS: #REF!
Name table: #REF!
Name table: #REF!
Name term: #REF!
Name term: #REF!
Name transfer: #REF!
Name transfer: #REF!
Name tv: #REF!
Name tv: #REF!
Name V: #REF!
Name V: #REF!
Name XXXX: #REF!
Name XXXX: #REF!

Sheet PEDIDO
B1: SOLICITUD DE PEDIDO SHERWIN WILLIAMS
B3: DISTRIBUIDOR: | D3: INVERSIONES TECNO BAHIA | F3: SUB-TOTAL = | G3: =SUM(G8:G107) -> 0
B4: REALIZADO POR: | D4: MARIA JOSE OSEGUEDA | F4: IVA = | G4: =G3*14% -> 0
B5: FECHA: | D5: =TODAY() -> 46141 | F5: TOTAL = | G5: =G3+G4 -> 0
B7: ITEM | C7: CODIGO | D7: DESCRIPCIÓN | E7: CANTIDAD | F7: COSTO UNITARIO | G7: IMPORTE
B8: 1 | F8: =IF(C8="","",IFERROR(VLOOKUP(C8,LISTA_COMPLETA!$A$1:$F$2388,3,FALSE),"ERROR")) | G8: =IF(C8="","",IFERROR(F8*E8,"ERROR"))
B9: =B8+1 -> 2 | F9: =IF(C9="","",IFERROR(VLOOKUP(C9,LISTA_COMPLETA!$A$1:$F$2388,3,FALSE),"ERROR")) | G9: =IF(C9="","",IFERROR(F9*E9,"ERROR"))
B10: =B9+1 -> 3 | F10: =IF(C10="","",IFERROR(VLOOKUP(C10,LISTA_COMPLETA!$A$1:$F$2388,3,FALSE),"ERROR")) | G10: =IF(C10="","",IFERROR(F10*E10,"ERROR"))
B11: =B10+1 -> 4 | F11: =IF(C11="","",IFERROR(VLOOKUP(C11,LISTA_COMPLETA!$A$1:$F$2388,3,FALSE),"ERROR")) | G11: =IF(C11="","",IFERROR(F11*E11,"ERROR"))
B12: =B11+1 -> 5 | F12: =IF(C12="","",IFERROR(VLOOKUP(C12,LISTA_COMPLETA!$A$1:$F$2388,3,FALSE),"ERROR")) | G12: =IF(C12="","",IFERROR(F12*E12,"ERROR"))
B13: =B12+1 -> 6 | F13: =IF(C13="","",IFERROR(VLOOKUP(C13,LISTA_COMPLETA!$A$1:$F$2388,3,FALSE),"ERROR")) | G13: =IF(C13="","",IFERROR(F13*E13,"ERROR"))
B14: =B13+1 -> 7 | F14: =IF(C14="","",IFERROR(VLOOKUP(C14,LISTA_COMPLETA!$A$1:$F$2388,3,FALSE),"ERROR")) | G14: =IF(C14="","",IFERROR(F14*E14,"ERROR"))
B15: =B14+1 -> 8 | F15: =IF(C15="","",IFERROR(VLOOKUP(C15,LISTA_COMPLETA!$A$1:$F$2388,3,FALSE),"ERROR")) | G15: =IF(C15="","",IFERROR(F15*E15,"ERROR"))
B16: =B15+1 -> 9 | F16: =IF(C16="","",IFERROR(VLOOKUP(C16,LISTA_COMPLETA!$A$1:$F$2388,3,FALSE),"ERROR")) | G16: =IF(C16="","",IFERROR(F16*E16,"ERROR"))
B17: =B16+1 -> 10 | F17: =IF(C17="","",IFERROR(VLOOKUP(C17,LISTA_COMPLETA!$A$1:$F$2388,3,FALSE),"ERROR")) | G17: =IF(C17="","",IFERROR(F17*E17,"ERROR"))
B18: =B17+1 -> 11 | F18: =IF(C18="","",IFERROR(VLOOKUP(C18,LISTA_COMPLETA!$A$1:$F$2388,3,FALSE),"ERROR")) | G18: =IF(C18="","",IFERROR(F18*E18,"ERROR"))
B19: =B18+1 -> 12 | F19: =IF(C19="","",IFERROR(VLOOKUP(C19,LISTA_COMPLETA!$A$1:$F$2388,3,FALSE),"ERROR")) | G19: =IF(C19="","",IFERROR(F19*E19,"ERROR"))
B20: =B19+1 -> 13 | F20: =IF(C20="","",IFERROR(VLOOKUP(C20,LISTA_COMPLETA!$A$1:$F$2388,3,FALSE),"ERROR")) | G20: =IF(C20="","",IFERROR(F20*E20,"ERROR"))
... B24: =B23+1 -> 17 | F24: =IF(C24="","",IFERROR(VLOOKUP(C24,LISTA_COMPLETA!$A$1:$F$2388,3,FALSE),"ERROR")) | G24: =IF(C24="","",IFERROR(F24*E24,"ERROR"))
B25: =B24+1 -> 18 | D25: =IF(C25="","",IFERROR(VLOOKUP(C25,LISTA_COMPLETA!$A$1:$F$2388,2,FALSE),"ESCRIBA CODIGO CORRECTO")) | F25: =IF(C25="","",IFERROR(VLOOKUP(C25,LISTA_COMPLETA!$A$1:$F$2388,3,FALSE),"ERROR")) | G25: =IF(C25="","",IFERROR(F25*E25,"ERROR"))
B26: =B25+1 -> 19 | D26: =IF(C26="","",IFERROR(VLOOKUP(C26,LISTA_COMPLETA!$A$1:$F$2388,2,FALSE),"ESCRIBA CODIGO CORRECTO")) | F26: =IF(C26="","",IFERROR(VLOOKUP(C26,LISTA_COMPLETA!$A$1:$F$2388,3,FALSE),"ERROR")) | G26: =IF(C26="","",IFERROR(F26*E26,"ERROR"))
B27: =B26+1 -> 20 | D27: =IF(C27="","",IFERROR(VLOOKUP(C27,LISTA_COMPLETA!$A$1:$F$2388,2,FALSE),"ESCRIBA CODIGO CORRECTO")) | F27: =IF(C27="","",IFERROR(VLOOKUP(C27,LISTA_COMPLETA!$A$1:$F$2388,3,FALSE),"ERROR")) | G27: =IF(C27="","",IFERROR(F27*E27,"ERROR"))
B28: =B27+1 -> 21 | D28: =IF(C28="","",IFERROR(VLOOKUP(C28,LISTA_COMPLETA!$A$1:$F$2388,2,FALSE),"ESCRIBA CODIGO CORRECTO")) | F28: =IF(C28="","",IFERROR(VLOOKUP(C28,LISTA_COMPLETA!$A$1:$F$2388,3,FALSE),"ERROR")) | G28: =IF(C28="","",IFERROR(F28*E28,"ERROR"))
B29: =B28+1 -> 22 | D29: =IF(C29="","",IFERROR(VLOOKUP(C29,LISTA_COMPLETA!$A$1:$F$2388,2,FALSE),"ESCRIBA CODIGO CORRECTO")) | F29: =IF(C29="","",IFERROR(VLOOKUP(C29,LISTA_COMPLETA!$A$1:$F$2388,3,FALSE),"ERROR")) | G29: =IF(C29="","",IFERROR(F29*E29,"ERROR"))
B30: =B29+1 -> 23 | D30: =IF(C30="","",IFERROR(VLOOKUP(C30,LISTA_COMPLETA!$A$1:$F$2388,2,FALSE),"ESCRIBA CODIGO CORRECTO")) | F30: =IF(C30="","",IFERROR(VLOOKUP(C30,LISTA_COMPLETA!$A$1:$F$2388,3,FALSE),"ERROR")) | G30: =IF(C30="","",IFERROR(F30*E30,"ERROR"))
B31: =B30+1 -> 24 | D31: =IF(C31="","",IFERROR(VLOOKUP(C31,LISTA_COMPLETA!$A$1:$F$2388,2,FALSE),"ESCRIBA CODIGO CORRECTO")) | F31: =IF(C31="","",IFERROR(VLOOKUP(C31,LISTA_COMPLETA!$A$1:$F$2388,3,FALSE),"ERROR")) | G31: =IF(C31="","",IFERROR(F31*E31,"ERROR"))
B32: =B31+1 -> 25 | D32: =IF(C32="","",IFERROR(VLOOKUP(C32,LISTA_COMPLETA!$A$1:$F$2388,2,FALSE),"ESCRIBA CODIGO CORRECTO")) | F32: =IF(C32="","",IFERROR(VLOOKUP(C32,LISTA_COMPLETA!$A$1:$F$2388,3,FALSE),"ERROR")) | G32: =IF(C32="","",IFERROR(F32*E32,"ERROR"))
B33: =B32+1 -> 26 | D33: =IF(C33="","",IFERROR(VLOOKUP(C33,LISTA_COMPLETA!$A$1:$F$2388,2,FALSE),"ESCRIBA CODIGO CORRECTO")) | F33: =IF(C33="","",IFERROR(VLOOKUP(C33,LISTA_COMPLETA!$A$1:$F$2388,3,FALSE),"ERROR")) | G33: =IF(C33="","",IFERROR(F33*E33,"ERROR"))
B34: =B33+1 -> 27 | D34: =IF(C34="","",IFERROR(VLOOKUP(C34,LISTA_COMPLETA!$A$1:$F$2388,2,FALSE),"ESCRIBA CODIGO CORRECTO")) | F34: =IF(C34="","",IFERROR(VLOOKUP(C34,LISTA_COMPLETA!$A$1:$F$2388,3,FALSE),"ERROR")) | G34: =IF(C34="","",IFERROR(F34*E34,"ERROR"))
B35: =B34+1 -> 28 | D35: =IF(C35="","",IFERROR(VLOOKUP(C35,LISTA_COMPLETA!$A$1:$F$2388,2,FALSE),"ESCRIBA CODIGO CORRECTO")) | F35: =IF(C35="","",IFERROR(VLOOKUP(C35,LISTA_COMPLETA!$A$1:$F$2388,3,FALSE),"ERROR")) | G35: =IF(C35="","",IFERROR(F35*E35,"ERROR"))
B36: =B35+1 -> 29 | D36: =IF(C36="","",IFERROR(VLOOKUP(C36,LISTA_COMPLETA!$A$1:$F$2388,2,FALSE),"ESCRIBA CODIGO CORRECTO")) | F36: =IF(C36="","",IFERROR(VLOOKUP(C36,LISTA_COMPLETA!$A$1:$F$2388,3,FALSE),"ERROR")) | G36: =IF(C36="","",IFERROR(F36*E36,"ERROR"))
... B107: =B106+1 -> 100 | D107: =IF(C107="","",IFERROR(VLOOKUP(C107,LISTA_COMPLETA!$A$1:$F$2388,2,FALSE),"ESCRIBA CODIGO CORRECTO")) | F107: =IF(C107="","",IFERROR(VLOOKUP(C107,LISTA_COMPLETA!$A$1:$F$2388,3,FALSE),"ERROR")) | G107: =IF(C107="","",IFERROR(F107*E107,"ERROR"))
F108: =IF(C108="","",IFERROR(VLOOKUP(C108,LISTA_COMPLETA!$A$1:$F$2388,3,FALSE),"ERROR"))

Sheet LISTA_COMPLETA
A2: CODIGOS | B2: DESCRIPCION DEL PRODUCTO | C2: PAD SIN IVA ABRIL 2026 | D2: PAD CON IVA ABRIL 2026 | E2: PSM SIN IVA ABRIL 2026 | F2: PSM CON IVA ABRIL 2026
A3: A24W451-1 | B3: LOXON XP MATE BASE EXTRA WHITE | C3: =VLOOKUP(A3,'[11]Linea Arquitectonica'!$A$4:$G$823,4,FALSE) -> 30.34 | D3: =VLOOKUP(A3,'[11]Linea Arquitectonica'!A4:E823,5,FALSE) -> 34.28 | E3: =VLOOKUP(A3,'[11]Linea Arquitectonica'!A4:F823,6,FALSE) -> 46.81 | F3: =VLOOKUP(A3,'[11]Linea Arquitectonica'!A4:G823,7,FALSE) -> 52.9
A4: A24W451-5 | B4: LOXON XP MATE BASE EXTRA WHITE | C4: =VLOOKUP(A4,'[11]Linea Arquitectonica'!$A$4:$G$823,4,FALSE) -> 139.34 | D4: =VLOOKUP(A4,'[11]Linea Arquitectonica'!A5:E824,5,FALSE) -> 157.45 | E4: =VLOOKUP(A4,'[11]Linea Arquitectonica'!A5:F824,6,FALSE) -> 215.93 | F4: =VLOOKUP(A4,'[11]Linea Arquitectonica'!A5:G824,7,FALSE) -> 244
A5: A24W453-1 | B5: LOXON XP MATE BASE DEEP | C5: =VLOOKUP(A5,'[11]Linea Arquitectonica'!$A$4:$G$823,4,FALSE) -> 26.83 | D5: =VLOOKUP(A5,'[11]Linea Arquitectonica'!A6:E825,5,FALSE) -> 30.32 | E5: =VLOOKUP(A5,'[11]Linea Arquitectonica'!A6:F825,6,FALSE) -> 46.81 | F5: =VLOOKUP(A5,'[11]Linea Arquitectonica'!A6:G825,7,FALSE) -> 52.9
A6: A24W453-5 | B6: LOXON XP MATE BASE DEEP | C6: =VLOOKUP(A6,'[11]Linea Arquitectonica'!$A$4:$G$823,4,FALSE) -> 121.83 | D6: =VLOOKUP(A6,'[11]Linea Arquitectonica'!A7:E826,5,FALSE) -> 137.67 | E6: =VLOOKUP(A6,'[11]Linea Arquitectonica'!A7:F826,6,FALSE) -> 215.93 | F6: =VLOOKUP(A6,'[11]Linea Arquitectonica'!A7:G826,7,FALSE) -> 244
A7: A24T454-1 | B7: LOXON XP MATE BASE ULTRA DEEP | C7: =VLOOKUP(A7,'[11]Linea Arquitectonica'!$A$4:$G$823,4,FALSE) -> 26.83 | D7: =VLOOKUP(A7,'[11]Linea Arquitectonica'!A8:E827,5,FALSE) -> 30.32 | E7: =VLOOKUP(A7,'[11]Linea Arquitectonica'!A8:F827,6,FALSE) -> 46.81 | F7: =VLOOKUP(A7,'[11]Linea Arquitectonica'!A8:G827,7,FALSE) -> 52.9
A8: A24T454-5 | B8: LOXON XP MATE BASE ULTRA DEEP | C8: =VLOOKUP(A8,'[11]Linea Arquitectonica'!$A$4:$G$823,4,FALSE) -> 121.83 | D8: =VLOOKUP(A8,'[11]Linea Arquitectonica'!A9:E828,5,FALSE) -> 137.67 | E8: =VLOOKUP(A8,'[11]Linea Arquitectonica'!A9:F828,6,FALSE) -> 215.93 | F8: =VLOOKUP(A8,'[11]Linea Arquitectonica'!A9:G828,7,FALSE) -> 244
A9: A24W457-1 | B9: LOXON XP MATE ULTRA BLANCO | C9: =VLOOKUP(A9,'[11]Linea Arquitectonica'!$A$4:$G$823,4,FALSE) -> 31.83 | D9: =VLOOKUP(A9,'[11]Linea Arquitectonica'!A10:E829,5,FALSE) -> 35.97 | E9: =VLOOKUP(A9,'[11]Linea Arquitectonica'!A10:F829,6,FALSE) -> 46.81 | F9: =VLOOKUP(A9,'[11]Linea Arquitectonica'!A10:G829,7,FALSE) -> 52.9
A10: A24W457-5 | B10: LOXON XP MATE ULTRA BLANCO | C10: =VLOOKUP(A10,'[11]Linea Arquitectonica'!$A$4:$G$823,4,FALSE) -> 146.83 | D10: =VLOOKUP(A10,'[11]Linea Arquitectonica'!A11:E830,5,FALSE) -> 165.92 | E10: =VLOOKUP(A10,'[11]Linea Arquitectonica'!A11:F830,6,FALSE) -> 215.93 | F10: =VLOOKUP(A10,'[11]Linea Arquitectonica'!A11:G830,7,FALSE) -> 244
A11: Y4RSA58-1 | B11: EXTERIOR ACCENT LATEX MATE BASE PRIMARY RED | C11: =VLOOKUP(A11,'[11]Linea Arquitectonica'!$A$4:$G$823,4,FALSE) -> 28.04 | D11: =VLOOKUP(A11,'[11]Linea Arquitectonica'!A12:E831,5,FALSE) -> 31.68 | E11: =VLOOKUP(A11,'[11]Linea Arquitectonica'!A12:F831,6,FALSE) -> 48.58 | F11: =VLOOKUP(A11,'[11]Linea Arquitectonica'!A12:G831,7,FALSE) -> 54.9
A12: Y4TSA54-1 | B12: EXTERIOR ACCENT LATEX MATE BASE CHROMA | C12: =VLOOKUP(A12,'[11]Linea Arquitectonica'!$A$4:$G$823,4,FALSE) -> 28.04 | D12: =VLOOKUP(A12,'[11]Linea Arquitectonica'!A13:E832,5,FALSE) -> 31.68 | E12: =VLOOKUP(A12,'[11]Linea Arquitectonica'!A13:F832,6,FALSE) -> 48.58 | F12: =VLOOKUP(A12,'[11]Linea Arquitectonica'!A13:G832,7,FALSE) -> 54.9
A13: Y4YSA57-1 | B13: EXTERIOR ACCENT LATEX MATE BASE VIVID YELLOW | C13: =VLOOKUP(A13,'[11]Linea Arquitectonica'!$A$4:$G$823,4,FALSE) -> 28.04 | D13: =VLOOKUP(A13,'[11]Linea Arquitectonica'!A13:E833,5,FALSE) -> 31.68 | E13: =VLOOKUP(A13,'[11]Linea Arquitectonica'!A13:F833,6,FALSE) -> 48.58 | F13: =VLOOKUP(A13,'[11]Linea Arquitectonica'!A13:G833,7,FALSE) -> 54.9
A14: Y4YSA57-5 | B14: EXTERIOR ACCENT LATEX MATE BASE VIVID YELLOW | C14: =VLOOKUP(A14,'[11]Linea Arquitectonica'!$A$4:$G$823,4,FALSE) -> 123.64 | D14: =VLOOKUP(A14,'[11]Linea Arquitectonica'!A14:E834,5,FALSE) -> 139.71 | E14: =VLOOKUP(A14,'[11]Linea Arquitectonica'!A14:F834,6,FALSE) -> 218.58 | F14: =VLOOKUP(A14,'[11]Linea Arquitectonica'!A14:G834,7,FALSE) -> 247
A15: Y4RSA158-1 | B15: EXTERIOR ACCENT LATEX SATINADO BASE PRIMARY RED | C15: =VLOOKUP(A15,'[11]Linea Arquitectonica'!$A$4:$G$823,4,FALSE) -> 29.6 | D15: =VLOOKUP(A15,'[11]Linea Arquitectonica'!A15:E835,5,FALSE) -> 33.45 | E15: =VLOOKUP(A15,'[11]Linea Arquitectonica'!A15:F835,6,FALSE) -> 50.88 | F15: =VLOOKUP(A15,'[11]Linea Arquitectonica'!A15:G835,7,FALSE) -> 57.5
A16: Y4TSA154-1 | B16: EXTERIOR ACCENT LATEX SATINADO BASE CHROMA | C16: =VLOOKUP(A16,'[11]Linea Arquitectonica'!$A$4:$G$823,4,FALSE) -> 29.6 | D16: =VLOOKUP(A16,'[11]Linea Arquitectonica'!A16:E836,5,FALSE) -> 33.45 | E16: =VLOOKUP(A16,'[11]Linea Arquitectonica'!A16:F836,6,FALSE) -> 50.88 | F16: =VLOOKUP(A16,'[11]Linea Arquitectonica'!A16:G836,7,FALSE) -> 57.5
A17: Y4YSA157-1 | B17: EXTERIOR ACCENT LATEX SATINADO BASE VIVID YELLOW | C17: =VLOOKUP(A17,'[11]Linea Arquitectonica'!$A$4:$G$823,4,FALSE) -> 29.6 | D17: =VLOOKUP(A17,'[11]Linea Arquitectonica'!A17:E837,5,FALSE) -> 33.45 | E17: =VLOOKUP(A17,'[11]Linea Arquitectonica'!A17:F837,6,FALSE) -> 50.88 | F17: =VLOOKUP(A17,'[11]Linea Arquitectonica'!A17:G837,7,FALSE) -> 57.5
A18: Y4YSA157-5 | B18: EXTERIOR ACCENT LATEX SATINADO BASE VIVID YELLOW | C18: =VLOOKUP(A18,'[11]Linea Arquitectonica'!$A$4:$G$823,4,FALSE) -> 126.04 | D18: =VLOOKUP(A18,'[11]Linea Arquitectonica'!A18:E838,5,FALSE) -> 142.43 | E18: =VLOOKUP(A18,'[11]Linea Arquitectonica'!A18:F838,6,FALSE) -> 222.12 | F18: =VLOOKUP(A18,'[11]Linea Arquitectonica'!A18:G838,7,FALSE) -> 251
A19: Y21YSA157-1/4 | B19: COLORACCENTS LATEX INTERIOR MATE BASE BRIGHT YELLOW | C19: =VLOOKUP(A19,'[11]Linea Arquitectonica'!$A$4:$G$823,4,FALSE) -> 7.23 | D19: =VLOOKUP(A19,'[11]Linea Arquitectonica'!A18:E839,5,FALSE) -> 8.17 | E19: =VLOOKUP(A19,'[11]Linea Arquitectonica'!A18:F839,6,FALSE) -> 12.83 | F19: =VLOOKUP(A19,'[11]Linea Arquitectonica'!A18:G839,7,FALSE) -> 14.5
A20: Y21RSA158-1/4 | B20: COLORACCENTS LATEX INTERIOR MATE BASE REAL RED | C20: =VLOOKUP(A20,'[11]Linea Arquitectonica'!$A$4:$G$823,4,FALSE) -> 7.23 | D20: =VLOOKUP(A20,'[11]Linea Arquitectonica'!A19:E840,5,FALSE) -> 8.17 | E20: =VLOOKUP(A20,'[11]Linea Arquitectonica'!A19:F840,6,FALSE) -> 12.83 | F20: =VLOOKUP(A20,'[11]Linea Arquitectonica'!A19:G840,7,FALSE) -> 14.5
A21: Y21TSA154-1/4 | B21: COLORACCENTS LATEX INTERIOR MATE BASE ULTRA DEEP | C21: =VLOOKUP(A21,'[11]Linea Arquitectonica'!$A$4:$G$823,4,FALSE) -> 7.23 | D21: =VLOOKUP(A21,'[11]Linea Arquitectonica'!A20:E841,5,FALSE) -> 8.17 | E21: =VLOOKUP(A21,'[11]Linea Arquitectonica'!A20:F841,6,FALSE) -> 12.83 | F21: =VLOOKUP(A21,'[11]Linea Arquitectonica'!A20:G841,7,FALSE) -> 14.5
A22: Y21YSA157-1 | B22: COLORACCENTS LATEX INTERIOR MATE BASE BRIGHT YELLOW | C22: =VLOOKUP(A22,'[11]Linea Arquitectonica'!$A$4:$G$823,4,FALSE) -> 24.79 | D22: =VLOOKUP(A22,'[11]Linea Arquitectonica'!A21:E842,5,FALSE) -> 28.01 | E22: =VLOOKUP(A22,'[11]Linea Arquitectonica'!A21:F842,6,FALSE) -> 43.81 | F22: =VLOOKUP(A22,'[11]Linea Arquitectonica'!A21:G842,7,FALSE) -> 49.5
A23: Y21RSA158-1 | B23: COLORACCENTS LATEX INTERIOR MATE BASE REAL RED | C23: =VLOOKUP(A23,'[11]Linea Arquitectonica'!$A$4:$G$823,4,FALSE) -> 24.79 | D23: =VLOOKUP(A23,'[11]Linea Arquitectonica'!A22:E843,5,FALSE) -> 28.01 | E23: =VLOOKUP(A23,'[11]Linea Arquitectonica'!A22:F843,6,FALSE) -> 43.81 | F23: =VLOOKUP(A23,'[11]Linea Arquitectonica'!A22:G843,7,FALSE) -> 49.5
A24: Y21TSA154-1 | B24: COLORACCENTS LATEX INTERIOR MATE BASE ULTRA DEEP | C24: =VLOOKUP(A24,'[11]Linea Arquitectonica'!$A$4:$G$823,4,FALSE) -> 24.79 | D24: =VLOOKUP(A24,'[11]Linea Arquitectonica'!A23:E844,5,FALSE) -> 28.01 | E24: =VLOOKUP(A24,'[11]Linea Arquitectonica'!A23:F844,6,FALSE) -> 43.81 | F24: =VLOOKUP(A24,'[11]Linea Arquitectonica'!A23:G844,7,FALSE) -> 49.5
A25: Y21TSA154-5 | B25: COLORACCENTS LATEX INTERIOR MATE BASE ULTRA DEEP | C25: =VLOOKUP(A25,'[11]Linea Arquitectonica'!$A$4:$G$823,4,FALSE) -> 103.78 | D25: =VLOOKUP(A25,'[11]Linea Arquitectonica'!A24:E845,5,FALSE) -> 117.27 | E25: =VLOOKUP(A25,'[11]Linea Arquitectonica'!A24:F845,6,FALSE) -> 189.38 | F25: =VLOOKUP(A25,'[11]Linea Arquitectonica'!A24:G845,7,FALSE) -> 214
A26: Y38YSA157-1 | B26: COLORACCENTS LATEX INTERIOR SATINADO BASE BRIGHT YELLOW | C26: =VLOOKUP(A26,'[11]Linea Arquitectonica'!$A$4:$G$823,4,FALSE) -> 25.39 | D26: =VLOOKUP(A26,'[11]Linea Arquitectonica'!A25:E846,5,FALSE) -> 28.69 | E26: =VLOOKUP(A26,'[11]Linea Arquitectonica'!A25:F846,6,FALSE) -> 44.69 | F26: =VLOOKUP(A26,'[11]Linea Arquitectonica'!A25:G846,7,FALSE) -> 50.5
A27: Y38RSA158-1 | B27: COLORACCENTS LATEX INTERIOR SATINADO BASE REAL RED | C27: =VLOOKUP(A27,'[11]Linea Arquitectonica'!$A$4:$G$823,4,FALSE) -> 25.39 | D27: =VLOOKUP(A27,'[11]Linea Arquitectonica'!A26:E847,5,FALSE) -> 28.69 | E27: =VLOOKUP(A27,'[11]Linea Arquitectonica'!A26:F847,6,FALSE) -> 44.69 | F27: =VLOOKUP(A27,'[11]Linea Arquitectonica'!A26:G847,7,FALSE) -> 50.5
A28: Y38TSA154-1 | B28: COLORACCENTS LATEX INTERIOR SATINADO BASE ULTRA DEEP | C28: =VLOOKUP(A28,'[11]Linea Arquitectonica'!$A$4:$G$823,4,FALSE) -> 25.39 | D28: =VLOOKUP(A28,'[11]Linea Arquitectonica'!A26:E848,5,FALSE) -> 28.69 | E28: =VLOOKUP(A28,'[11]Linea Arquitectonica'!A26:F848,6,FALSE) -> 44.69 | F28: =VLOOKUP(A28,'[11]Linea Arquitectonica'!A26:G848,7,FALSE) -> 50.5
A29: Y14TSA154-1 | B29: COLORACCENTS ALKYD INTERIOR SEMI BRILLANTE BASE ULTRADEEP | C29: =VLOOKUP(A29,'[11]Linea Arquitectonica'!$A$4:$G$823,4,FALSE) -> 40.07 | D29: =VLOOKUP(A29,'[11]Linea Arquitectonica'!A27:E849,5,FALSE) -> 45.28 | E29: =VLOOKUP(A29,'[11]Linea Arquitectonica'!A27:F849,6,FALSE) -> 66.28 | F29: =VLOOKUP(A29,'[11]Linea Arquitectonica'!A27:G849,7,FALSE) -> 74.9
A30: A86WSA51-1/4 | B30: SUPERPAINT INTERIOR MATE BASE EXTRA WHITE | C30: =VLOOKUP(A30,'[11]Linea Arquitectonica'!$A$4:$G$823,4,FALSE) -> 7.63 | D30: =VLOOKUP(A30,'[11]Linea Arquitectonica'!A28:E850,5,FALSE) -> 8.62 | E30: =VLOOKUP(A30,'[11]Linea Arquitectonica'!A28:F850,6,FALSE) -> 11.95 | F30: =VLOOKUP(A30,'[11]Linea Arquitectonica'!A28:G850,7,FALSE) -> 13.5
A31: A86WSA53-1/4 | B31: SUPERPAINT INTERIOR MATE BASE DEEP | C31: =VLOOKUP(A31,'[11]Linea Arquitectonica'!$A$4:$G$823,4,FALSE) -> 6.63 | D31: =VLOOKUP(A31,'[11]Linea Arquitectonica'!A29:E851,5,FALSE) -> 7.49 | E31: =VLOOKUP(A31,'[11]Linea Arquitectonica'!A29:F851,6,FALSE) -> 11.95 | F31: =VLOOKUP(A31,'[11]Linea Arquitectonica'!A29:G851,7,FALSE) -> 13.5
A32: A86TSA54-1/4 | B32: SUPERPAINT INTERIOR MATE BASE ULTRA DEEP | C32: =VLOOKUP(A32,'[11]Linea Arquitectonica'!$A$4:$G$823,4,FALSE) -> 6.63 | D32: =VLOOKUP(A32,'[11]Linea Arquitectonica'!A30:E852,5,FALSE) -> 7.49 | E32: =VLOOKUP(A32,'[11]Linea Arquitectonica'!A30:F852,6,FALSE) -> 11.95 | F32: =VLOOKUP(A32,'[11]Linea Arquitectonica'!A30:G852,7,FALSE) -> 13.5
A33: A86W57-1 | B33: SUPERPAINT INTERIOR MATE BLANCO | C33: =VLOOKUP(A33,'[11]Linea Arquitectonica'!$A$4:$G$823,4,FALSE) -> 28.58 | D33: =VLOOKUP(A33,'[11]Linea Arquitectonica'!A31:E853,5,FALSE) -> 32.3 | E33: =VLOOKUP(A33,'[11]Linea Arquitectonica'!A31:F853,6,FALSE) -> 42.04 | F33: =VLOOKUP(A33,'[11]Linea Arquitectonica'!A31:G853,7,FALSE) -> 47.5
A34: A86WSA51-1 | B34: SUPERPAINT INTERIOR MATE BASE EXTRA WHITE | C34: =VLOOKUP(A34,'[11]Linea Arquitectonica'!$A$4:$G$823,4,FALSE) -> 27.09 | D34: =VLOOKUP(A34,'[11]Linea Arquitectonica'!A32:E854,5,FALSE) -> 30.61 | E34: =VLOOKUP(A34,'[11]Linea Arquitectonica'!A32:F854,6,FALSE) -> 42.04 | F34: =VLOOKUP(A34,'[11]Linea Arquitectonica'!A32:G854,7,FALSE) -> 47.5
A35: A86WSA53-1 | B35: SUPERPAINT INTERIOR MATE BASE DEEP | C35: =VLOOKUP(A35,'[11]Linea Arquitectonica'!$A$4:$G$823,4,FALSE) -> 23.58 | D35: =VLOOKUP(A35,'[11]Linea Arquitectonica'!A32:E855,5,FALSE) -> 26.65 | E35: =VLOOKUP(A35,'[11]Linea Arquitectonica'!A32:F855,6,FALSE) -> 42.04 | F35: =VLOOKUP(A35,'[11]Linea Arquitectonica'!A32:G855,7,FALSE) -> 47.5
A36: A86TSA54-1 | B36: SUPERPAINT INTERIOR MATE BASE ULTRA DEEP | C36: =VLOOKUP(A36,'[11]Linea Arquitectonica'!$A$4:$G$823,4,FALSE) -> 23.58 | D36: =VLOOKUP(A36,'[11]Linea Arquitectonica'!A32:E856,5,FALSE) -> 26.65 | E36: =VLOOKUP(A36,'[11]Linea Arquitectonica'!A32:F856,6,FALSE) -> 42.04 | F36: =VLOOKUP(A36,'[11]Linea Arquitectonica'!A32:G856,7,FALSE) -> 47.5
A37: A86W57-5 | B37: SUPERPAINT INTERIOR MATE BLANCO | C37: =VLOOKUP(A37,'[11]Linea Arquitectonica'!$A$4:$G$823,4,FALSE) -> 136 | D37: =VLOOKUP(A37,'[11]Linea Arquitectonica'!A33:E857,5,FALSE) -> 153.68 | E37: =VLOOKUP(A37,'[11]Linea Arquitectonica'!A33:F857,6,FALSE) -> 200 | F37: =VLOOKUP(A37,'[11]Linea Arquitectonica'!A33:G857,7,FALSE) -> 226
A38: A86WSA51-5 | B38: SUPERPAINT INTERIOR MATE BASE EXTRA WHITE | C38: =VLOOKUP(A38,'[11]Linea Arquitectonica'!$A$4:$G$823,4,FALSE) -> 128.5 | D38: =VLOOKUP(A38,'[11]Linea Arquitectonica'!A34:E858,5,FALSE) -> 145.21 | E38: =VLOOKUP(A38,'[11]Linea Arquitectonica'!A34:F858,6,FALSE) -> 200 | F38: =VLOOKUP(A38,'[11]Linea Arquitectonica'!A34:G858,7,FALSE) -> 226
A39: A86WSA53-5 | B39: SUPERPAINT INTERIOR MATE BASE DEEP | C39: =VLOOKUP(A39,'[11]Linea Arquitectonica'!$A$4:$G$823,4,FALSE) -> 111 | D39: =VLOOKUP(A39,'[11]Linea Arquitectonica'!A35:E859,5,FALSE) -> 125.43 | E39: =VLOOKUP(A39,'[11]Linea Arquitectonica'!A35:F859,6,FALSE) -> 200 | F39: =VLOOKUP(A39,'[11]Linea Arquitectonica'!A35:G859,7,FALSE) -> 226
A40: A86TSA54-5 | B40: SUPERPAINT INTERIOR MATE BASE ULTRA DEEP | C40: =VLOOKUP(A40,'[11]Linea Arquitectonica'!$A$4:$G$823,4,FALSE) -> 111 | D40: =VLOOKUP(A40,'[11]Linea Arquitectonica'!A36:E860,5,FALSE) -> 125.43 | E40: =VLOOKUP(A40,'[11]Linea Arquitectonica'!A36:F860,6,FALSE) -> 200 | F40: =VLOOKUP(A40,'[11]Linea Arquitectonica'!A36:G860,7,FALSE) -> 226
A41: A87WSA1-1 | B41: SUPERPAINT INTERIOR LATEX SATINADO BLANCO | C41: =VLOOKUP(A41,'[11]Linea Arquitectonica'!$A$4:$G$823,4,FALSE) -> 29.79 | D41: =VLOOKUP(A41,'[11]Linea Arquitectonica'!A37:E861,5,FALSE) -> 33.66 | E41: =VLOOKUP(A41,'[11]Linea Arquitectonica'!A37:F861,6,FALSE) -> 43.81 | F41: =VLOOKUP(A41,'[11]Linea Arquitectonica'!A37:G861,7,FALSE) -> 49.5
A42: A87TSA54-1 | B42: SUPERPAINT INTERIOR LATEX SATINADO ULTRA DEEP | C42: =VLOOKUP(A42,'[11]Linea Arquitectonica'!$A$4:$G$823,4,FALSE) -> 24.79 | D42: =VLOOKUP(A42,'[11]Linea Arquitectonica'!A38:E862,5,FALSE) -> 28.01 | E42: =VLOOKUP(A42,'[11]Linea Arquitectonica'!A38:F862,6,FALSE) -> 43.81 | F42: =VLOOKUP(A42,'[11]Linea Arquitectonica'!A38:G862,7,FALSE) -> 49.5
A43: A87WSA51-1 | B43: SUPERPAINT INTERIOR LATEX SATINADO EXTRA WHITE | C43: =VLOOKUP(A43,'[11]Linea Arquitectonica'!$A$4:$G$823,4,FALSE) -> 28.29 | D43: =VLOOKUP(A43,'[11]Linea Arquitectonica'!A39:E863,5,FALSE) -> 31.97 | E43: =VLOOKUP(A43,'[11]Linea Arquitectonica'!A39:F863,6,FALSE) -> 43.81 | F43: =VLOOKUP(A43,'[11]Linea Arquitectonica'!A39:G863,7,FALSE) -> 49.5
A44: A87WSA53-1 | B44: SUPERPAINT INTERIOR LATEX SATINADO DEEP | C44: =VLOOKUP(A44,'[11]Linea Arquitectonica'!$A$4:$G$823,4,FALSE) -> 24.79 | D44: =VLOOKUP(A44,'[11]Linea Arquitectonica'!A40:E864,5,FALSE) -> 28.01 | E44: =VLOOKUP(A44,'[11]Linea Arquitectonica'!A40:F864,6,FALSE) -> 43.81 | F44: =VLOOKUP(A44,'[11]Linea Arquitectonica'!A40:G864,7,FALSE) -> 49.5
A45: A87WSA1-5 | B45: SUPERPAINT INTERIOR LATEX SATINADO BLANCO | C45: =VLOOKUP(A45,'[11]Linea Arquitectonica'!$A$4:$G$823,4,FALSE) -> 138.41 | D45: =VLOOKUP(A45,'[11]Linea Arquitectonica'!A41:E865,5,FALSE) -> 156.4 | E45: =VLOOKUP(A45,'[11]Linea Arquitectonica'!A41:F865,6,FALSE) -> 203.54 | F45: =VLOOKUP(A45,'[11]Linea Arquitectonica'!A41:G865,7,FALSE) -> 230
A46: A87TSA54-5 | B46: SUPERPAINT INTERIOR LATEX SATINADO ULTRA DEEP | C46: =VLOOKUP(A46,'[11]Linea Arquitectonica'!$A$4:$G$823,4,FALSE) -> 113.41 | D46: =VLOOKUP(A46,'[11]Linea Arquitectonica'!A42:E866,5,FALSE) -> 128.15 | E46: =VLOOKUP(A46,'[11]Linea Arquitectonica'!A42:F866,6,FALSE) -> 203.54 | F46: =VLOOKUP(A46,'[11]Linea Arquitectonica'!A42:G866,7,FALSE) -> 230
A47: A87WSA51-5 | B47: SUPERPAINT INTERIOR LATEX SATINADO EXTRA WHITE | C47: =VLOOKUP(A47,'[11]Linea Arquitectonica'!$A$4:$G$823,4,FALSE) -> 130.91 | D47: =VLOOKUP(A47,'[11]Linea Arquitectonica'!A43:E867,5,FALSE) -> 147.93 | E47: =VLOOKUP(A47,'[11]Linea Arquitectonica'!A43:F867,6,FALSE) -> 203.54 | F47: =VLOOKUP(A47,'[11]Linea Arquitectonica'!A43:G867,7,FALSE) -> 230
... A50: A80WSA51-1/4 | B50: SUPERPAINT EXTERIOR MATE BASE EXTRA WHITE | C50: =VLOOKUP(A50,'[11]Linea Arquitectonica'!$A$4:$G$823,4,FALSE) -> 8.47 | D50: =VLOOKUP(A50,'[11]Linea Arquitectonica'!A46:E870,5,FALSE) -> 9.57 | E50: =VLOOKUP(A50,'[11]Linea Arquitectonica'!A46:F870,6,FALSE) -> 13.19 | F50: =VLOOKUP(A50,'[11]Linea Arquitectonica'!A46:G870,7,FALSE) -> 14.9
A51: A80WSA53-1/4 | B51: SUPERPAINT EXTERIOR MATE BASE DEEP | C51: =VLOOKUP(A51,'[11]Linea Arquitectonica'!$A$4:$G$823,4,FALSE) -> 7.47 | D51: =VLOOKUP(A51,'[11]Linea Arquitectonica'!A46:E871,5,FALSE) -> 8.44 | E51: =VLOOKUP(A51,'[11]Linea Arquitectonica'!A46:F871,6,FALSE) -> 13.19 | F51: =VLOOKUP(A51,'[11]Linea Arquitectonica'!A46:G871,7,FALSE) -> 14.9
A52: A80TSA54-1/4 | B52: SUPERPAINT EXTERIOR MATE BASE ULTRA DEEP | C52: =VLOOKUP(A52,'[11]Linea Arquitectonica'!$A$4:$G$823,4,FALSE) -> 7.47 | D52: =VLOOKUP(A52,'[11]Linea Arquitectonica'!A47:E872,5,FALSE) -> 8.44 | E52: =VLOOKUP(A52,'[11]Linea Arquitectonica'!A47:F872,6,FALSE) -> 13.19 | F52: =VLOOKUP(A52,'[11]Linea Arquitectonica'!A47:G872,7,FALSE) -> 14.9
A53: A80TSA54-1 | B53: SUPERPAINT EXTERIOR MATE BASE ULTRA DEEP | C53: =VLOOKUP(A53,'[11]Linea Arquitectonica'!$A$4:$G$823,4,FALSE) -> 25.39 | D53: =VLOOKUP(A53,'[11]Linea Arquitectonica'!A48:E873,5,FALSE) -> 28.69 | E53: =VLOOKUP(A53,'[11]Linea Arquitectonica'!A48:F873,6,FALSE) -> 44.69 | F53: =VLOOKUP(A53,'[11]Linea Arquitectonica'!A48:G873,7,FALSE) -> 50.5
A54: A80WSA51-1 | B54: SUPERPAINT EXTERIOR MATE BASE EXTRA WHITE | C54: =VLOOKUP(A54,'[11]Linea Arquitectonica'!$A$4:$G$823,4,FALSE) -> 28.89 | D54: =VLOOKUP(A54,'[11]Linea Arquitectonica'!A49:E874,5,FALSE) -> 32.65 | E54: =VLOOKUP(A54,'[11]Linea Arquitectonica'!A49:F874,6,FALSE) -> 44.69 | F54: =VLOOKUP(A54,'[11]Linea Arquitectonica'!A49:G874,7,FALSE) -> 50.5
A55: A80WSA53-1 | B55: SUPERPAINT EXTERIOR MATE BASE DEEP | C55: =VLOOKUP(A55,'[11]Linea Arquitectonica'!$A$4:$G$823,4,FALSE) -> 25.39 | D55: =VLOOKUP(A55,'[11]Linea Arquitectonica'!A50:E875,5,FALSE) -> 28.69 | E55: =VLOOKUP(A55,'[11]Linea Arquitectonica'!A50:F875,6,FALSE) -> 44.69 | F55: =VLOOKUP(A55,'[11]Linea Arquitectonica'!A50:G875,7,FALSE) -> 50.5
A56: A80YSA56-1 | B56: SUPERPAINT EXTERIOR MATE BASE LIGHT YELLOW | C56: =VLOOKUP(A56,'[11]Linea Arquitectonica'!$A$4:$G$823,4,FALSE) -> 25.39 | D56: =VLOOKUP(A56,'[11]Linea Arquitectonica'!A51:E876,5,FALSE) -> 28.69 | E56: =VLOOKUP(A56,'[11]Linea Arquitectonica'!A51:F876,6,FALSE) -> 44.69 | F56: =VLOOKUP(A56,'[11]Linea Arquitectonica'!A51:G876,7,FALSE) -> 50.5
A57: A80WSA1-1 | B57: SUPERPAINT EXTERIOR LATEX MATE WHITE | C57: =VLOOKUP(A57,'[11]Linea Arquitectonica'!$A$4:$G$823,4,FALSE) -> 30.39 | D57: =VLOOKUP(A57,'[11]Linea Arquitectonica'!A52:E877,5,FALSE) -> 34.34 | E57: =VLOOKUP(A57,'[11]Linea Arquitectonica'!A52:F877,6,FALSE) -> 44.69 | F57: =VLOOKUP(A57,'[11]Linea Arquitectonica'!A52:G877,7,FALSE) -> 50.5
A58: A80TSA54-5 | B58: SUPERPAINT EXTERIOR MATE BASE ULTRA DEEP | C58: =VLOOKUP(A58,'[11]Linea Arquitectonica'!$A$4:$G$823,4,FALSE) -> 117.62 | D58: =VLOOKUP(A58,'[11]Linea Arquitectonica'!A53:E878,5,FALSE) -> 132.91 | E58: =VLOOKUP(A58,'[11]Linea Arquitectonica'!A53:F878,6,FALSE) -> 209.73 | F58: =VLOOKUP(A58,'[11]Linea Arquitectonica'!A53:G878,7,FALSE) -> 237
A59: A80WSA51-5 | B59: SUPERPAINT EXTERIOR MATE BASE EXTRA WHITE | C59: =VLOOKUP(A59,'[11]Linea Arquitectonica'!$A$4:$G$823,4,FALSE) -> 135.12 | D59: =VLOOKUP(A59,'[11]Linea Arquitectonica'!A53:E879,5,FALSE) -> 152.69 | E59: =VLOOKUP(A59,'[11]Linea Arquitectonica'!A53:F879,6,FALSE) -> 209.73 | F59: =VLOOKUP(A59,'[11]Linea Arquitectonica'!A53:G879,7,FALSE) -> 237
A60: A80WSA53-5 | B60: SUPERPAINT EXTERIOR MATE BASE DEEP | C60: =VLOOKUP(A60,'[11]Linea Arquitectonica'!$A$4:$G$823,4,FALSE) -> 117.62 | D60: =VLOOKUP(A60,'[11]Linea Arquitectonica'!A54:E880,5,FALSE) -> 132.91 | E60: =VLOOKUP(A60,'[11]Linea Arquitectonica'!A54:F880,6,FALSE) -> 209.73 | F60: =VLOOKUP(A60,'[11]Linea Arquitectonica'!A54:G880,7,FALSE) -> 237
A61: A80YSA56-5 | B61: SUPERPAINT EXTERIOR MATE BASE LIGHT YELLOW | C61: =VLOOKUP(A61,'[11]Linea Arquitectonica'!$A$4:$G$823,4,FALSE) -> 117.62 | D61: =VLOOKUP(A61,'[11]Linea Arquitectonica'!A55:E881,5,FALSE) -> 132.91 | E61: =VLOOKUP(A61,'[11]Linea Arquitectonica'!A55:F881,6,FALSE) -> 209.73 | F61: =VLOOKUP(A61,'[11]Linea Arquitectonica'!A55:G881,7,FALSE) -> 237
A62: A80WSA1-5 | B62: SUPERPAINT EXTERIOR LATEX MATE WHITE | C62: =VLOOKUP(A62,'[11]Linea Arquitectonica'!$A$4:$G$823,4,FALSE) -> 142.62 | D62: =VLOOKUP(A62,'[11]Linea Arquitectonica'!A60:E882,5,FALSE) -> 161.16 | E62: =VLOOKUP(A62,'[11]Linea Arquitectonica'!A60:F882,6,FALSE) -> 209.73 | F62: =VLOOKUP(A62,'[11]Linea Arquitectonica'!A60:G882,7,FALSE) -> 237
A63: A89WSA51-1/4 | B63: SUPERPAINT EXTERIOR SATINADO BASE EXTRA WHITE | C63: =VLOOKUP(A63,'[11]Linea Arquitectonica'!$A$4:$G$823,4,FALSE) -> 8.83 | D63: =VLOOKUP(A63,'[11]Linea Arquitectonica'!A61:E883,5,FALSE) -> 9.98 | E63: =VLOOKUP(A63,'[11]Linea Arquitectonica'!A61:F883,6,FALSE) -> 13.72 | F63: =VLOOKUP(A63,'[11]Linea Arquitectonica'!A61:G883,7,FALSE) -> 15.5
A64: A89WSA53-1/4 | B64: SUPERPAINT EXTERIOR SATINADO BASE DEEP | C64: =VLOOKUP(A64,'[11]Linea Arquitectonica'!$A$4:$G$823,4,FALSE) -> 7.83 | D64: =VLOOKUP(A64,'[11]Linea Arquitectonica'!A62:E884,5,FALSE) -> 8.85 | E64: =VLOOKUP(A64,'[11]Linea Arquitectonica'!A62:F884,6,FALSE) -> 13.72 | F64: =VLOOKUP(A64,'[11]Linea Arquitectonica'!A62:G884,7,FALSE) -> 15.5
A65: A89TSA54-1/4 | B65: SUPERPAINT EXTERIOR SATINADO BASE ULTRA DEEP | C65: =VLOOKUP(A65,'[11]Linea Arquitectonica'!$A$4:$G$823,4,FALSE) -> 7.83 | D65: =VLOOKUP(A65,'[11]Linea Arquitectonica'!A63:E885,5,FALSE) -> 8.85 | E65: =VLOOKUP(A65,'[11]Linea Arquitectonica'!A63:F885,6,FALSE) -> 13.72 | F65: =VLOOKUP(A65,'[11]Linea Arquitectonica'!A63:G885,7,FALSE) -> 15.5
A66: A89TSA54-1 | B66: SUPERPAINT EXTERIOR SATINADO BASE ULTRA DEEP | C66: =VLOOKUP(A66,'[11]Linea Arquitectonica'!$A$4:$G$823,4,FALSE) -> 26.59 | D66: =VLOOKUP(A66,'[11]Linea Arquitectonica'!A64:E886,5,FALSE) -> 30.05 | E66: =VLOOKUP(A66,'[11]Linea Arquitectonica'!A64:F886,6,FALSE) -> 46.46 | F66: =VLOOKUP(A66,'[11]Linea Arquitectonica'!A64:G886,7,FALSE) -> 52.5
A67: A89WSA51-1 | B67: SUPERPAINT EXTERIOR SATINADO BASE EXTRA WHITE | C67: =VLOOKUP(A67,'[11]Linea Arquitectonica'!$A$4:$G$823,4,FALSE) -> 30.1 | D67: =VLOOKUP(A67,'[11]Linea Arquitectonica'!A65:E887,5,FALSE) -> 34.01 | E67: =VLOOKUP(A67,'[11]Linea Arquitectonica'!A65:F887,6,FALSE) -> 46.46 | F67: =VLOOKUP(A67,'[11]Linea Arquitectonica'!A65:G887,7,FALSE) -> 52.5
A68: A89WSA53-1 | B68: SUPERPAINT EXTERIOR SATINADO BASE DEEP | C68: =VLOOKUP(A68,'[11]Linea Arquitectonica'!$A$4:$G$823,4,FALSE) -> 26.59 | D68: =VLOOKUP(A68,'[11]Linea Arquitectonica'!A66:E888,5,FALSE) -> 30.05 | E68: =VLOOKUP(A68,'[11]Linea Arquitectonica'!A66:F888,6,FALSE) -> 46.46 | F68: =VLOOKUP(A68,'[11]Linea Arquitectonica'!A66:G888,7,FALSE) -> 52.5
A69: A89YSA56-1 | B69: SUPERPAINT EXTERIOR SATINADO BASE LIGHT YELLOW | C69: =VLOOKUP(A69,'[11]Linea Arquitectonica'!$A$4:$G$823,4,FALSE) -> 26.59 | D69: =VLOOKUP(A69,'[11]Linea Arquitectonica'!A67:E889,5,FALSE) -> 30.05 | E69: =VLOOKUP(A69,'[11]Linea Arquitectonica'!A67:F889,6,FALSE) -> 46.46 | F69: =VLOOKUP(A69,'[11]Linea Arquitectonica'!A67:G889,7,FALSE) -> 52.5
A70: A89WSA1-1 | B70: SUPERPAINT EXTERIOR SATINADO BLANCO | C70: =VLOOKUP(A70,'[11]Linea Arquitectonica'!$A$4:$G$823,4,FALSE) -> 31.59 | D70: =VLOOKUP(A70,'[11]Linea Arquitectonica'!A68:E890,5,FALSE) -> 35.7 | E70: =VLOOKUP(A70,'[11]Linea Arquitectonica'!A68:F890,6,FALSE) -> 46.46 | F70: =VLOOKUP(A70,'[11]Linea Arquitectonica'!A68:G890,7,FALSE) -> 52.5
A71: A89TSA54-5 | B71: SUPERPAINT EXTERIOR SATINADO BASE ULTRA DEEP | C71: =VLOOKUP(A71,'[11]Linea Arquitectonica'!$A$4:$G$823,4,FALSE) -> 118.82 | D71: =VLOOKUP(A71,'[11]Linea Arquitectonica'!A69:E891,5,FALSE) -> 134.27 | E71: =VLOOKUP(A71,'[11]Linea Arquitectonica'!A69:F891,6,FALSE) -> 211.5 | F71: =VLOOKUP(A71,'[11]Linea Arquitectonica'!A69:G891,7,FALSE) -> 239
A72: A89WSA51-5 | B72: SUPERPAINT EXTERIOR SATINADO BASE EXTRA WHITE | C72: =VLOOKUP(A72,'[11]Linea Arquitectonica'!$A$4:$G$823,4,FALSE) -> 136.33 | D72: =VLOOKUP(A72,'[11]Linea Arquitectonica'!A70:E892,5,FALSE) -> 154.05 | E72: =VLOOKUP(A72,'[11]Linea Arquitectonica'!A70:F892,6,FALSE) -> 211.5 | F72: =VLOOKUP(A72,'[11]Linea Arquitectonica'!A70:G892,7,FALSE) -> 239
A73: A89WSA53-5 | B73: SUPERPAINT EXTERIOR SATINADO BASE DEEP | C73: =VLOOKUP(A73,'[11]Linea Arquitectonica'!$A$4:$G$823,4,FALSE) -> 118.82 | D73: =VLOOKUP(A73,'[11]Linea Arquitectonica'!A71:E893,5,FALSE) -> 134.27 | E73: =VLOOKUP(A73,'[11]Linea Arquitectonica'!A71:F893,6,FALSE) -> 211.5 | F73: =VLOOKUP(A73,'[11]Linea Arquitectonica'!A71:G893,7,FALSE) -> 239
... A79: B5TSA6054-1 | B79: SHERTECH 6000 LATEX ULTRA MATE BASE ULTRA DEEP | C79: =VLOOKUP(A79,'[11]Linea Arquitectonica'!$A$4:$G$823,4,FALSE) -> 18.23 | D79: =VLOOKUP(A79,'[11]Linea Arquitectonica'!A77:E899,5,FALSE) -> 20.6 | E79: =VLOOKUP(A79,'[11]Linea Arquitectonica'!A77:F899,6,FALSE) -> 33.19 | F79: =VLOOKUP(A79,'[11]Linea Arquitectonica'!A77:G899,7,FALSE) -> 37.5
A80: B5WSA61-5 | B80: SHERTECH 6000 LATEX ULTRA MATE BLANCO | C80: =VLOOKUP(A80,'[11]Linea Arquitectonica'!$A$4:$G$823,4,FALSE) -> 100.35 | D80: =VLOOKUP(A80,'[11]Linea Arquitectonica'!A77:E900,5,FALSE) -> 113.4 | E80: =VLOOKUP(A80,'[11]Linea Arquitectonica'!A77:F900,6,FALSE) -> 143.36 | F80: =VLOOKUP(A80,'[11]Linea Arquitectonica'!A77:G900,7,FALSE) -> 162
A81: B5WSA6051-5 | B81: SHERTECH 6000 LATEX ULTRA MATE BASE EXTRA WHITE | C81: =VLOOKUP(A81,'[11]Linea Arquitectonica'!$A$4:$G$823,4,FALSE) -> 92.86 | D81: =VLOOKUP(A81,'[11]Linea Arquitectonica'!A78:E901,5,FALSE) -> 104.93 | E81: =VLOOKUP(A81,'[11]Linea Arquitectonica'!A78:F901,6,FALSE) -> 143.36 | F81: =VLOOKUP(A81,'[11]Linea Arquitectonica'!A78:G901,7,FALSE) -> 162
A82: B5WSA6053-5 | B82: SHERTECH 6000 LATEX ULTRA MATE BASE DEEP | C82: =VLOOKUP(A82,'[11]Linea Arquitectonica'!$A$4:$G$823,4,FALSE) -> 75.35 | D82: =VLOOKUP(A82,'[11]Linea Arquitectonica'!A79:E902,5,FALSE) -> 85.15 | E82: =VLOOKUP(A82,'[11]Linea Arquitectonica'!A79:F902,6,FALSE) -> 143.36 | F82: =VLOOKUP(A82,'[11]Linea Arquitectonica'!A79:G902,7,FALSE) -> 162
A83: B5TSA6054-5 | B83: SHERTECH 6000 LATEX ULTRA MATE BASE ULTRA DEEP | C83: =VLOOKUP(A83,'[11]Linea Arquitectonica'!$A$4:$G$823,4,FALSE) -> 75.35 | D83: =VLOOKUP(A83,'[11]Linea Arquitectonica'!A80:E903,5,FALSE) -> 85.15 | E83: =VLOOKUP(A83,'[11]Linea Arquitectonica'!A80:F903,6,FALSE) -> 143.36 | F83: =VLOOKUP(A83,'[11]Linea Arquitectonica'!A80:G903,7,FALSE) -> 162
A84: B79WSA28-1 | B84: SHERTECH 4000 LATEX ULTRA MATE BLANCO | C84: =VLOOKUP(A84,'[11]Linea Arquitectonica'!$A$4:$G$823,4,FALSE) -> 21.62 | D84: =VLOOKUP(A84,'[11]Linea Arquitectonica'!A81:E904,5,FALSE) -> 24.43 | E84: =VLOOKUP(A84,'[11]Linea Arquitectonica'!A81:F904,6,FALSE) -> 30.88 | F84: =VLOOKUP(A84,'[11]Linea Arquitectonica'!A81:G904,7,FALSE) -> 34.9
A85: B79WSA4051-1 | B85: SHERTECH 4000 LATEX ULTRA MATE BASE EXTRA WHITE | C85: =VLOOKUP(A85,'[11]Linea Arquitectonica'!$A$4:$G$823,4,FALSE) -> 20.12 | D85: =VLOOKUP(A85,'[11]Linea Arquitectonica'!A82:E905,5,FALSE) -> 22.74 | E85: =VLOOKUP(A85,'[11]Linea Arquitectonica'!A82:F905,6,FALSE) -> 30.88 | F85: =VLOOKUP(A85,'[11]Linea Arquitectonica'!A82:G905,7,FALSE) -> 34.9
A86: B79WSA4053-1 | B86: SHERTECH 4000 LATEX ULTRA MATE BASE DEEP | C86: =VLOOKUP(A86,'[11]Linea Arquitectonica'!$A$4:$G$823,4,FALSE) -> 16.62 | D86: =VLOOKUP(A86,'[11]Linea Arquitectonica'!A83:E906,5,FALSE) -> 18.78 | E86: =VLOOKUP(A86,'[11]Linea Arquitectonica'!A83:F906,6,FALSE) -> 30.88 | F86: =VLOOKUP(A86,'[11]Linea Arquitectonica'!A83:G906,7,FALSE) -> 34.9
A87: B79TSA4054-1 | B87: SHERTECH 4000 LATEX ULTRA MATE BASE ULTRA DEEP | C87: =VLOOKUP(A87,'[11]Linea Arquitectonica'!$A$4:$G$823,4,FALSE) -> 16.62 | D87: =VLOOKUP(A87,'[11]Linea Arquitectonica'!A89:E907,5,FALSE) -> 18.78 | E87: =VLOOKUP(A87,'[11]Linea Arquitectonica'!A89:F907,6,FALSE) -> 30.88 | F87: =VLOOKUP(A87,'[11]Linea Arquitectonica'!A89:G907,7,FALSE) -> 34.9
A88: B79WSA28-5 | B88: SHERTECH 4000 LATEX ULTRA MATE BLANCO | C88: =VLOOKUP(A88,'[11]Linea Arquitectonica'!$A$4:$G$823,4,FALSE) -> 94.16 | D88: =VLOOKUP(A88,'[11]Linea Arquitectonica'!A90:E908,5,FALSE) -> 106.4 | E88: =VLOOKUP(A88,'[11]Linea Arquitectonica'!A90:F908,6,FALSE) -> 134.51 | F88: =VLOOKUP(A88,'[11]Linea Arquitectonica'!A90:G908,7,FALSE) -> 152
A89: B79WSA4051-5 | B89: SHERTECH 4000 LATEX ULTRA MATE BASE EXTRA WHITE | C89: =VLOOKUP(A89,'[11]Linea Arquitectonica'!$A$4:$G$823,4,FALSE) -> 86.66 | D89: =VLOOKUP(A89,'[11]Linea Arquitectonica'!A91:E909,5,FALSE) -> 97.93 | E89: =VLOOKUP(A89,'[11]Linea Arquitectonica'!A91:F909,6,FALSE) -> 134.51 | F89: =VLOOKUP(A89,'[11]Linea Arquitectonica'!A91:G909,7,FALSE) -> 152
A90: B79WSA4053-5 | B90: SHERTECH 4000 LATEX ULTRA MATE BASE DEEP | C90: =VLOOKUP(A90,'[11]Linea Arquitectonica'!$A$4:$G$823,4,FALSE) -> 69.16 | D90: =VLOOKUP(A90,'[11]Linea Arquitectonica'!A92:E910,5,FALSE) -> 78.15 | E90: =VLOOKUP(A90,'[11]Linea Arquitectonica'!A92:F910,6,FALSE) -> 134.51 | F90: =VLOOKUP(A90,'[11]Linea Arquitectonica'!A92:G910,7,FALSE) -> 152
A91: B79TSA4054-5 | B91: SHERTECH 4000 LATEX ULTRA MATE BASE ULTRA DEEP | C91: =VLOOKUP(A91,'[11]Linea Arquitectonica'!$A$4:$G$823,4,FALSE) -> 69.16 | D91: =VLOOKUP(A91,'[11]Linea Arquitectonica'!A93:E911,5,FALSE) -> 78.15 | E91: =VLOOKUP(A91,'[11]Linea Arquitectonica'!A93:F911,6,FALSE) -> 134.51 | F91: =VLOOKUP(A91,'[11]Linea Arquitectonica'!A93:G911,7,FALSE) -> 152
A92: A28W57-1 | B92: EXCELLO ONE COAT BLANCO | C92: =VLOOKUP(A92,'[11]Linea Arquitectonica'!$A$4:$G$823,4,FALSE) -> 24.63 | D92: =VLOOKUP(A92,'[11]Linea Arquitectonica'!A94:E912,5,FALSE) -> 27.83 | E92: =VLOOKUP(A92,'[11]Linea Arquitectonica'!A94:F912,6,FALSE) -> 35.31 | F92: =VLOOKUP(A92,'[11]Linea Arquitectonica'!A94:G912,7,FALSE) -> 39.9
A93: A28W57-5 | B93: EXCELLO ONE COAT BLANCO | C93: =VLOOKUP(A93,'[11]Linea Arquitectonica'!$A$4:$G$823,4,FALSE) -> 116.27 | D93: =VLOOKUP(A93,'[11]Linea Arquitectonica'!A95:E913,5,FALSE) -> 131.39 | E93: =VLOOKUP(A93,'[11]Linea Arquitectonica'!A95:F913,6,FALSE) -> 167.26 | F93: =VLOOKUP(A93,'[11]Linea Arquitectonica'!A95:G913,7,FALSE) -> 189
A94: B5RSA17-1/4 | B94: EXCELLO LATEX MATE ROJO LADRILLO QUEMADO | C94: =VLOOKUP(A94,'[11]Linea Arquitectonica'!$A$4:$G$823,4,FALSE) -> 7.12 | D94: =VLOOKUP(A94,'[11]Linea Arquitectonica'!A96:E914,5,FALSE) -> 8.05 | E94: =VLOOKUP(A94,'[11]Linea Arquitectonica'!A96:F914,6,FALSE) -> 10.18 | F94: =VLOOKUP(A94,'[11]Linea Arquitectonica'!A96:G914,7,FALSE) -> 11.5
A95: B5WSA7-1/4 | B95: EXCELLO LATEX MATE BLANCO HUESO | C95: =VLOOKUP(A95,'[11]Linea Arquitectonica'!$A$4:$G$823,4,FALSE) -> 7.12 | D95: =VLOOKUP(A95,'[11]Linea Arquitectonica'!A97:E915,5,FALSE) -> 8.05 | E95: =VLOOKUP(A95,'[11]Linea Arquitectonica'!A97:F915,6,FALSE) -> 10.18 | F95: =VLOOKUP(A95,'[11]Linea Arquitectonica'!A97:G915,7,FALSE) -> 11.5
A96: B5WSA10-1/4 | B96: EXCELLO LATEX MATE BLANCO DOVER | C96: =VLOOKUP(A96,'[11]Linea Arquitectonica'!$A$4:$G$823,4,FALSE) -> 7.12 | D96: =VLOOKUP(A96,'[11]Linea Arquitectonica'!A98:E916,5,FALSE) -> 8.05 | E96: =VLOOKUP(A96,'[11]Linea Arquitectonica'!A98:F916,6,FALSE) -> 10.18 | F96: =VLOOKUP(A96,'[11]Linea Arquitectonica'!A98:G916,7,FALSE) -> 11.5
A97: B5W57-1/4 | B97: EXCELLO LATEX MATE BLANCO | C97: =VLOOKUP(A97,'[11]Linea Arquitectonica'!$A$4:$G$823,4,FALSE) -> 7.12 | D97: =VLOOKUP(A97,'[11]Linea Arquitectonica'!A99:E917,5,FALSE) -> 8.05 | E97: =VLOOKUP(A97,'[11]Linea Arquitectonica'!A99:F917,6,FALSE) -> 10.18 | F97: =VLOOKUP(A97,'[11]Linea Arquitectonica'!A99:G917,7,FALSE) -> 11.5
A98: B5A36-1 | B98: EXCELLO LATEX MATE GRIS PERLA | C98: =VLOOKUP(A98,'[11]Linea Arquitectonica'!$A$4:$G$823,4,FALSE) -> 22.24 | D98: =VLOOKUP(A98,'[11]Linea Arquitectonica'!A100:E918,5,FALSE) -> 25.13 | E98: =VLOOKUP(A98,'[11]Linea Arquitectonica'!A100:F918,6,FALSE) -> 31.77 | F98: =VLOOKUP(A98,'[11]Linea Arquitectonica'!A100:G918,7,FALSE) -> 35.9
... A100: B5ESA3-1 | B100: EXCELLO LATEX MATE MELOCOTÓN | C100: =VLOOKUP(A100,'[11]Linea Arquitectonica'!$A$4:$G$823,4,FALSE) -> 22.24 | D100: =VLOOKUP(A100,'[11]Linea Arquitectonica'!A102:E920,5,FALSE) -> 25.13 | E100: =VLOOKUP(A100,'[11]Linea Arquitectonica'!A102:F920,6,FALSE) -> 31.77 | F100: =VLOOKUP(A100,'[11]Linea Arquitectonica'!A102:G920,7,FALSE) -> 35.9
A101: B5ESA11-1 | B101: EXCELLO LATEX MATE MELON | C101: =VLOOKUP(A101,'[11]Linea Arquitectonica'!$A$4:$G$823,4,FALSE) -> 22.24 | D101: =VLOOKUP(A101,'[11]Linea Arquitectonica'!A107:E921,5,FALSE) -> 25.13 | E101: =VLOOKUP(A101,'[11]Linea Arquitectonica'!A107:F921,6,FALSE) -> 31.77 | F101: =VLOOKUP(A101,'[11]Linea Arquitectonica'!A107:G921,7,FALSE) -> 35.9
A102: B5G84-1 | B102: EXCELLO LATEX MATE VERDE ALEGRE | C102: =VLOOKUP(A102,'[11]Linea Arquitectonica'!$A$4:$G$823,4,FALSE) -> 22.24 | D102: =VLOOKUP(A102,'[11]Linea Arquitectonica'!A108:E922,5,FALSE) -> 25.13 | E102: =VLOOKUP(A102,'[11]Linea Arquitectonica'!A108:F922,6,FALSE) -> 31.77 | F102: =VLOOKUP(A102,'[11]Linea Arquitectonica'!A108:G922,7,FALSE) -> 35.9
A103: B5GSA56-1 | B103: EXCELLO LATEX MATE VERDE CARYMAR | C103: =VLOOKUP(A103,'[11]Linea Arquitectonica'!$A$4:$G$823,4,FALSE) -> 22.24 | D103: =VLOOKUP(A103,'[11]Linea Arquitectonica'!A109:E923,5,FALSE) -> 25.13 | E103: =VLOOKUP(A103,'[11]Linea Arquitectonica'!A109:F923,6,FALSE) -> 31.77 | F103: =VLOOKUP(A103,'[11]Linea Arquitectonica'!A109:G923,7,FALSE) -> 35.9
A104: B5H22-1 | B104: EXCELLO LATEX MATE MARFIL | C104: =VLOOKUP(A104,'[11]Linea Arquitectonica'!$A$4:$G$823,4,FALSE) -> 22.24 | D104: =VLOOKUP(A104,'[11]Linea Arquitectonica'!A110:E924,5,FALSE) -> 25.13 | E104: =VLOOKUP(A104,'[11]Linea Arquitectonica'!A110:F924,6,FALSE) -> 31.77 | F104: =VLOOKUP(A104,'[11]Linea Arquitectonica'!A110:G924,7,FALSE) -> 35.9
A105: B5HSA6-1 | B105: EXCELLO LATEX MATE MARFIL SUAVE | C105: =VLOOKUP(A105,'[11]Linea Arquitectonica'!$A$4:$G$823,4,FALSE) -> 22.24 | D105: =VLOOKUP(A105,'[11]Linea Arquitectonica'!A111:E925,5,FALSE) -> 25.13 | E105: =VLOOKUP(A105,'[11]Linea Arquitectonica'!A111:F925,6,FALSE) -> 31.77 | F105: =VLOOKUP(A105,'[11]Linea Arquitectonica'!A111:G925,7,FALSE) -> 35.9
A106: B5LSA5-1 | B106: EXCELLO LATEX MATE AZUL CENICIENTA | C106: =VLOOKUP(A106,'[11]Linea Arquitectonica'!$A$4:$G$823,4,FALSE) -> 22.24 | D106: =VLOOKUP(A106,'[11]Linea Arquitectonica'!A112:E926,5,FALSE) -> 25.13 | E106: =VLOOKUP(A106,'[11]Linea Arquitectonica'!A112:F926,6,FALSE) -> 31.77 | F106: =VLOOKUP(A106,'[11]Linea Arquitectonica'!A112:G926,7,FALSE) -> 35.9
A107: B5LSA10-1 | B107: EXCELLO LATEX MATE CELESTE INFINITO | C107: =VLOOKUP(A107,'[11]Linea Arquitectonica'!$A$4:$G$823,4,FALSE) -> 22.24 | D107: =VLOOKUP(A107,'[11]Linea Arquitectonica'!A113:E927,5,FALSE) -> 25.13 | E107: =VLOOKUP(A107,'[11]Linea Arquitectonica'!A113:F927,6,FALSE) -> 31.77 | F107: =VLOOKUP(A107,'[11]Linea Arquitectonica'!A113:G927,7,FALSE) -> 35.9
A108: B5LSA47-1 | B108: EXCELLO LATEX MATE AZUL INFINITO | C108: =VLOOKUP(A108,'[11]Linea Arquitectonica'!$A$4:$G$823,4,FALSE) -> 22.24 | D108: =VLOOKUP(A108,'[11]Linea Arquitectonica'!A114:E928,5,FALSE) -> 25.13 | E108: =VLOOKUP(A108,'[11]Linea Arquitectonica'!A114:F928,6,FALSE) -> 31.77 | F108: =VLOOKUP(A108,'[11]Linea Arquitectonica'!A114:G928,7,FALSE) -> 35.9
A109: B5N62-1 | B109: EXCELLO LATEX MATE BEIGE ARENA | C109: =VLOOKUP(A109,'[11]Linea Arquitectonica'!$A$4:$G$823,4,FALSE) -> 22.24 | D109: =VLOOKUP(A109,'[11]Linea Arquitectonica'!A115:E929,5,FALSE) -> 25.13 | E109: =VLOOKUP(A109,'[11]Linea Arquitectonica'!A115:F929,6,FALSE) -> 31.77 | F109: =VLOOKUP(A109,'[11]Linea Arquitectonica'!A115:G929,7,FALSE) -> 35.9
...
